[
{"Year":2005,"Cause":{"of":{"Death":"Heart Disease"}},"State":{"FIPS":{"Code":"MT"}},"HHS":{"Region":8},"Age":{"Range":"0-54"},"Benchmark":"Floating","Locality":"All","Observed":{"Deaths":158},"Population":699822,"Expected":{"Deaths":112},"Potentially":{"Excess":{"Deaths":46}}},
{"Year":2006,"Cause":{"of":{"Death":"Heart Disease"}},"State":{"FIPS":{"Code":"MT"}},"HHS":{"Region":8},"Age":{"Range":"0-54"},"Benchmark":"Floating","Locality":"All","Observed":{"Deaths":165},"Population":702856,"Expected":{"Deaths":113},"Potentially":{"Excess":{"Deaths":52}}},
{"Year":2007,"Cause":{"of":{"Death":"Heart Disease"}},"State":{"FIPS":{"Code":"MT"}},"HHS":{"Region":8},"Age":{"Range":"0-54"},"Benchmark":"Floating","Locality":"All","Observed":{"Deaths":149},"Population":705210,"Expected":{"Deaths":110},"Potentially":{"Excess":{"Deaths":39}}},
{"Year":2008,"Cause":{"of":{"Death":"Heart Disease"}},"State":{"FIPS":{"Code":"MT"}},"HHS":{"Region":8},"Age":{"Range":"0-54"},"Benchmark":"Floating","Locality":"All","Observed":{"Deaths":153},"Population":707295,"Expected":{"Deaths":110},"Potentially":{"Excess":{"Deaths":43}}},
{"Year":2009,"Cause":{"of":{"Death":"Heart Disease"}},"State":{"FIPS":{"Code":"MT"}},"HHS":{"Region":8},"Age":{"Range":"0-54"},"Benchmark":"Floating","Locality":"All","Observed":{"Deaths":128},"Population":705489,"Expected":{"Deaths":107},"Potentially":{"Excess":{"Deaths":24}}},
{"Year":2010,"Cause":{"of":{"Death":"Heart Disease"}},"State":{"FIPS":{"Code":"MT"}},"HHS":{"Region":8},"Age":{"Range":"0-54"},"Benchmark":"Floating","Locality":"All","Observed":{"Deaths":152},"Population":703815,"Expected":{"Deaths":103},"Potentially":{"Excess":{"Deaths":49}}},
{"Year":2011,"Cause":{"of":{"Death":"Heart Disease"}},"State":{"FIPS":{"Code":"MT"}},"HHS":{"Region":8},"Age":{"Range":"0-54"},"Benchmark":"Floating","Locality":"All","Observed":{"Deaths":156},"Population":701820,"Expected":{"Deaths":96},"Potentially":{"Excess":{"Deaths":60}}},
{"Year":2012,"Cause":{"of":{"Death":"Heart Disease"}},"State":{"FIPS":{"Code":"MT"}},"HHS":{"Region":8},"Age":{"Range":"0-54"},"Benchmark":"Floating","Locality":"All","Observed":{"Deaths":131},"Population":700019,"Expected":{"Deaths":93},"Potentially":{"Excess":{"Deaths":38}}},
{"Year":2013,"Cause":{"of":{"Death":"Heart Disease"}},"State":{"FIPS":{"Code":"MT"}},"HHS":{"Region":8},"Age":{"Range":"0-54"},"Benchmark":"Floating","Locality":"All","Observed":{"Deaths":124},"Population":701241,"Expected":{"Deaths":93},"Potentially":{"Excess":{"Deaths":33}}},
{"Year":2014,"Cause":{"of":{"Death":"Heart Disease"}},"State":{"FIPS":{"Code":"MT"}},"HHS":{"Region":8},"Age":{"Range":"0-54"},"Benchmark":"Floating","Locality":"All","Observed":{"Deaths":112},"Population":702030,"Expected":{"Deaths":90},"Potentially":{"Excess":{"Deaths":23}}},
{"Year":2015,"Cause":{"of":{"Death":"Heart Disease"}},"State":{"FIPS":{"Code":"MT"}},"HHS":{"Region":8},"Age":{"Range":"0-54"},"Benchmark":"Floating","Locality":"All","Observed":{"Deaths":134},"Population":703459,"Expected":{"Deaths":86},"Potentially":{"Excess":{"Deaths":51}}},
{"Year":2005,"Cause":{"of":{"Death":"Heart Disease"}},"State":{"FIPS":{"Code":"MT"}},"HHS":{"Region":8},"Age":{"Range":"0-54"},"Benchmark":"Floating","Locality":"Metropolitan","Observed":{"Deaths":45},"Population":252496,"Expected":{"Deaths":38},"Potentially":{"Excess":{"Deaths":7}}},
{"Year":2006,"Cause":{"of":{"Death":"Heart Disease"}},"State":{"FIPS":{"Code":"MT"}},"HHS":{"Region":8},"Age":{"Range":"0-54"},"Benchmark":"Floating","Locality":"Metropolitan","Observed":{"Deaths":58},"Population":253594,"Expected":{"Deaths":39},"Potentially":{"Excess":{"Deaths":19}}},
{"Year":2007,"Cause":{"of":{"Death":"Heart Disease"}},"State":{"FIPS":{"Code":"MT"}},"HHS":{"Region":8},"Age":{"Range":"0-54"},"Benchmark":"Floating","Locality":"Metropolitan","Observed":{"Deaths":44},"Population":254188,"Expected":{"Deaths":38},"Potentially":{"Excess":{"Deaths":8}}},
{"Year":2008,"Cause":{"of":{"Death":"Heart Disease"}},"State":{"FIPS":{"Code":"MT"}},"HHS":{"Region":8},"Age":{"Range":"0-54"},"Benchmark":"Floating","Locality":"Metropolitan","Observed":{"Deaths":49},"Population":255895,"Expected":{"Deaths":38},"Potentially":{"Excess":{"Deaths":12}}},
{"Year":2009,"Cause":{"of":{"Death":"Heart Disease"}},"State":{"FIPS":{"Code":"MT"}},"HHS":{"Region":8},"Age":{"Range":"0-54"},"Benchmark":"Floating","Locality":"Metropolitan","Observed":{"Deaths":40},"Population":256236,"Expected":{"Deaths":37},"Potentially":{"Excess":{"Deaths":7}}},
{"Year":2010,"Cause":{"of":{"Death":"Heart Disease"}},"State":{"FIPS":{"Code":"MT"}},"HHS":{"Region":8},"Age":{"Range":"0-54"},"Benchmark":"Floating","Locality":"Metropolitan","Observed":{"Deaths":40},"Population":256590,"Expected":{"Deaths":36},"Potentially":{"Excess":{"Deaths":6}}},
{"Year":2011,"Cause":{"of":{"Death":"Heart Disease"}},"State":{"FIPS":{"Code":"MT"}},"HHS":{"Region":8},"Age":{"Range":"0-54"},"Benchmark":"Floating","Locality":"Metropolitan","Observed":{"Deaths":51},"Population":256685,"Expected":{"Deaths":34},"Potentially":{"Excess":{"Deaths":18}}},
{"Year":2012,"Cause":{"of":{"Death":"Heart Disease"}},"State":{"FIPS":{"Code":"MT"}},"HHS":{"Region":8},"Age":{"Range":"0-54"},"Benchmark":"Floating","Locality":"Metropolitan","Observed":{"Deaths":46},"Population":256385,"Expected":{"Deaths":33},"Potentially":{"Excess":{"Deaths":14}}},
{"Year":2013,"Cause":{"of":{"Death":"Heart Disease"}},"State":{"FIPS":{"Code":"MT"}},"HHS":{"Region":8},"Age":{"Range":"0-54"},"Benchmark":"Floating","Locality":"Metropolitan","Observed":{"Deaths":43},"Population":257514,"Expected":{"Deaths":33},"Potentially":{"Excess":{"Deaths":12}}},
{"Year":2014,"Cause":{"of":{"Death":"Heart Disease"}},"State":{"FIPS":{"Code":"MT"}},"HHS":{"Region":8},"Age":{"Range":"0-54"},"Benchmark":"Floating","Locality":"Metropolitan","Observed":{"Deaths":35},"Population":257654,"Expected":{"Deaths":31},"Potentially":{"Excess":{"Deaths":6}}},
{"Year":2015,"Cause":{"of":{"Death":"Heart Disease"}},"State":{"FIPS":{"Code":"MT"}},"HHS":{"Region":8},"Age":{"Range":"0-54"},"Benchmark":"Floating","Locality":"Metropolitan","Observed":{"Deaths":46},"Population":257598,"Expected":{"Deaths":30},"Potentially":{"Excess":{"Deaths":16}}},
{"Year":2005,"Cause":{"of":{"Death":"Heart Disease"}},"State":{"FIPS":{"Code":"MT"}},"HHS":{"Region":8},"Age":{"Range":"0-54"},"Benchmark":"Floating","Locality":"Nonmetropolitan","Observed":{"Deaths":113},"Population":447326,"Expected":{"Deaths":74},"Potentially":{"Excess":{"Deaths":39}}},
{"Year":2006,"Cause":{"of":{"Death":"Heart Disease"}},"State":{"FIPS":{"Code":"MT"}},"HHS":{"Region":8},"Age":{"Range":"0-54"},"Benchmark":"Floating","Locality":"Nonmetropolitan","Observed":{"Deaths":107},"Population":449262,"Expected":{"Deaths":74},"Potentially":{"Excess":{"Deaths":33}}},
{"Year":2007,"Cause":{"of":{"Death":"Heart Disease"}},"State":{"FIPS":{"Code":"MT"}},"HHS":{"Region":8},"Age":{"Range":"0-54"},"Benchmark":"Floating","Locality":"Nonmetropolitan","Observed":{"Deaths":105},"Population":451022,"Expected":{"Deaths":73},"Potentially":{"Excess":{"Deaths":35}}},
{"Year":2008,"Cause":{"of":{"Death":"Heart Disease"}},"State":{"FIPS":{"Code":"MT"}},"HHS":{"Region":8},"Age":{"Range":"0-54"},"Benchmark":"Floating","Locality":"Nonmetropolitan","Observed":{"Deaths":104},"Population":451400,"Expected":{"Deaths":72},"Potentially":{"Excess":{"Deaths":32}}},
{"Year":2009,"Cause":{"of":{"Death":"Heart Disease"}},"State":{"FIPS":{"Code":"MT"}},"HHS":{"Region":8},"Age":{"Range":"0-54"},"Benchmark":"Floating","Locality":"Nonmetropolitan","Observed":{"Deaths":88},"Population":449253,"Expected":{"Deaths":70},"Potentially":{"Excess":{"Deaths":19}}},
{"Year":2010,"Cause":{"of":{"Death":"Heart Disease"}},"State":{"FIPS":{"Code":"MT"}},"HHS":{"Region":8},"Age":{"Range":"0-54"},"Benchmark":"Floating","Locality":"Nonmetropolitan","Observed":{"Deaths":112},"Population":447225,"Expected":{"Deaths":67},"Potentially":{"Excess":{"Deaths":45}}},
{"Year":2011,"Cause":{"of":{"Death":"Heart Disease"}},"State":{"FIPS":{"Code":"MT"}},"HHS":{"Region":8},"Age":{"Range":"0-54"},"Benchmark":"Floating","Locality":"Nonmetropolitan","Observed":{"Deaths":105},"Population":445135,"Expected":{"Deaths":63},"Potentially":{"Excess":{"Deaths":42}}},
{"Year":2012,"Cause":{"of":{"Death":"Heart Disease"}},"State":{"FIPS":{"Code":"MT"}},"HHS":{"Region":8},"Age":{"Range":"0-54"},"Benchmark":"Floating","Locality":"Nonmetropolitan","Observed":{"Deaths":85},"Population":443634,"Expected":{"Deaths":61},"Potentially":{"Excess":{"Deaths":24}}},
{"Year":2013,"Cause":{"of":{"Death":"Heart Disease"}},"State":{"FIPS":{"Code":"MT"}},"HHS":{"Region":8},"Age":{"Range":"0-54"},"Benchmark":"Floating","Locality":"Nonmetropolitan","Observed":{"Deaths":81},"Population":443727,"Expected":{"Deaths":61},"Potentially":{"Excess":{"Deaths":22}}},
{"Year":2014,"Cause":{"of":{"Death":"Heart Disease"}},"State":{"FIPS":{"Code":"MT"}},"HHS":{"Region":8},"Age":{"Range":"0-54"},"Benchmark":"Floating","Locality":"Nonmetropolitan","Observed":{"Deaths":77},"Population":444376,"Expected":{"Deaths":58},"Potentially":{"Excess":{"Deaths":19}}},
{"Year":2015,"Cause":{"of":{"Death":"Heart Disease"}},"State":{"FIPS":{"Code":"MT"}},"HHS":{"Region":8},"Age":{"Range":"0-54"},"Benchmark":"Floating","Locality":"Nonmetropolitan","Observed":{"Deaths":88},"Population":445861,"Expected":{"Deaths":56},"Potentially":{"Excess":{"Deaths":35}}},
{"Year":2005,"Cause":{"of":{"Death":"Cancer"}},"State":{"FIPS":{"Code":"MT"}},"HHS":{"Region":8},"Age":{"Range":"0-54"},"Benchmark":"Floating","Locality":"All","Observed":{"Deaths":227},"Population":699822,"Expected":{"Deaths":171},"Potentially":{"Excess":{"Deaths":57}}},
{"Year":2006,"Cause":{"of":{"Death":"Cancer"}},"State":{"FIPS":{"Code":"MT"}},"HHS":{"Region":8},"Age":{"Range":"0-54"},"Benchmark":"Floating","Locality":"All","Observed":{"Deaths":192},"Population":702856,"Expected":{"Deaths":176},"Potentially":{"Excess":{"Deaths":18}}},
{"Year":2007,"Cause":{"of":{"Death":"Cancer"}},"State":{"FIPS":{"Code":"MT"}},"HHS":{"Region":8},"Age":{"Range":"0-54"},"Benchmark":"Floating","Locality":"All","Observed":{"Deaths":194},"Population":705210,"Expected":{"Deaths":178},"Potentially":{"Excess":{"Deaths":24}}},
{"Year":2008,"Cause":{"of":{"Death":"Cancer"}},"State":{"FIPS":{"Code":"MT"}},"HHS":{"Region":8},"Age":{"Range":"0-54"},"Benchmark":"Floating","Locality":"All","Observed":{"Deaths":155},"Population":707295,"Expected":{"Deaths":172},"Potentially":{"Excess":{"Deaths":2}}},
{"Year":2009,"Cause":{"of":{"Death":"Cancer"}},"State":{"FIPS":{"Code":"MT"}},"HHS":{"Region":8},"Age":{"Range":"0-54"},"Benchmark":"Floating","Locality":"All","Observed":{"Deaths":221},"Population":705489,"Expected":{"Deaths":165},"Potentially":{"Excess":{"Deaths":56}}},
{"Year":2010,"Cause":{"of":{"Death":"Cancer"}},"State":{"FIPS":{"Code":"MT"}},"HHS":{"Region":8},"Age":{"Range":"0-54"},"Benchmark":"Floating","Locality":"All","Observed":{"Deaths":194},"Population":703815,"Expected":{"Deaths":165},"Potentially":{"Excess":{"Deaths":31}}},
{"Year":2011,"Cause":{"of":{"Death":"Cancer"}},"State":{"FIPS":{"Code":"MT"}},"HHS":{"Region":8},"Age":{"Range":"0-54"},"Benchmark":"Floating","Locality":"All","Observed":{"Deaths":199},"Population":701820,"Expected":{"Deaths":157},"Potentially":{"Excess":{"Deaths":42}}},
{"Year":2012,"Cause":{"of":{"Death":"Cancer"}},"State":{"FIPS":{"Code":"MT"}},"HHS":{"Region":8},"Age":{"Range":"0-54"},"Benchmark":"Floating","Locality":"All","Observed":{"Deaths":187},"Population":700019,"Expected":{"Deaths":154},"Potentially":{"Excess":{"Deaths":36}}},
{"Year":2013,"Cause":{"of":{"Death":"Cancer"}},"State":{"FIPS":{"Code":"MT"}},"HHS":{"Region":8},"Age":{"Range":"0-54"},"Benchmark":"Floating","Locality":"All","Observed":{"Deaths":147},"Population":701241,"Expected":{"Deaths":144},"Potentially":{"Excess":{"Deaths":7}}},
{"Year":2014,"Cause":{"of":{"Death":"Cancer"}},"State":{"FIPS":{"Code":"MT"}},"HHS":{"Region":8},"Age":{"Range":"0-54"},"Benchmark":"Floating","Locality":"All","Observed":{"Deaths":154},"Population":702030,"Expected":{"Deaths":140},"Potentially":{"Excess":{"Deaths":16}}},
{"Year":2015,"Cause":{"of":{"Death":"Cancer"}},"State":{"FIPS":{"Code":"MT"}},"HHS":{"Region":8},"Age":{"Range":"0-54"},"Benchmark":"Floating","Locality":"All","Observed":{"Deaths":193},"Population":703459,"Expected":{"Deaths":132},"Potentially":{"Excess":{"Deaths":62}}},
{"Year":2005,"Cause":{"of":{"Death":"Cancer"}},"State":{"FIPS":{"Code":"MT"}},"HHS":{"Region":8},"Age":{"Range":"0-54"},"Benchmark":"Floating","Locality":"Metropolitan","Observed":{"Deaths":63},"Population":252496,"Expected":{"Deaths":59},"Potentially":{"Excess":{"Deaths":6}}},
{"Year":2006,"Cause":{"of":{"Death":"Cancer"}},"State":{"FIPS":{"Code":"MT"}},"HHS":{"Region":8},"Age":{"Range":"0-54"},"Benchmark":"Floating","Locality":"Metropolitan","Observed":{"Deaths":72},"Population":253594,"Expected":{"Deaths":60},"Potentially":{"Excess":{"Deaths":12}}},
{"Year":2007,"Cause":{"of":{"Death":"Cancer"}},"State":{"FIPS":{"Code":"MT"}},"HHS":{"Region":8},"Age":{"Range":"0-54"},"Benchmark":"Floating","Locality":"Metropolitan","Observed":{"Deaths":52},"Population":254188,"Expected":{"Deaths":61},"Potentially":{"Excess":{"Deaths":3}}},
{"Year":2008,"Cause":{"of":{"Death":"Cancer"}},"State":{"FIPS":{"Code":"MT"}},"HHS":{"Region":8},"Age":{"Range":"0-54"},"Benchmark":"Floating","Locality":"Metropolitan","Observed":{"Deaths":60},"Population":255895,"Expected":{"Deaths":59},"Potentially":{"Excess":{"Deaths":3}}},
{"Year":2009,"Cause":{"of":{"Death":"Cancer"}},"State":{"FIPS":{"Code":"MT"}},"HHS":{"Region":8},"Age":{"Range":"0-54"},"Benchmark":"Floating","Locality":"Metropolitan","Observed":{"Deaths":78},"Population":256236,"Expected":{"Deaths":57},"Potentially":{"Excess":{"Deaths":22}}},
{"Year":2010,"Cause":{"of":{"Death":"Cancer"}},"State":{"FIPS":{"Code":"MT"}},"HHS":{"Region":8},"Age":{"Range":"0-54"},"Benchmark":"Floating","Locality":"Metropolitan","Observed":{"Deaths":61},"Population":256590,"Expected":{"Deaths":57},"Potentially":{"Excess":{"Deaths":8}}},
{"Year":2011,"Cause":{"of":{"Death":"Cancer"}},"State":{"FIPS":{"Code":"MT"}},"HHS":{"Region":8},"Age":{"Range":"0-54"},"Benchmark":"Floating","Locality":"Metropolitan","Observed":{"Deaths":76},"Population":256685,"Expected":{"Deaths":55},"Potentially":{"Excess":{"Deaths":24}}},
{"Year":2012,"Cause":{"of":{"Death":"Cancer"}},"State":{"FIPS":{"Code":"MT"}},"HHS":{"Region":8},"Age":{"Range":"0-54"},"Benchmark":"Floating","Locality":"Metropolitan","Observed":{"Deaths":65},"Population":256385,"Expected":{"Deaths":54},"Potentially":{"Excess":{"Deaths":12}}},
{"Year":2013,"Cause":{"of":{"Death":"Cancer"}},"State":{"FIPS":{"Code":"MT"}},"HHS":{"Region":8},"Age":{"Range":"0-54"},"Benchmark":"Floating","Locality":"Metropolitan","Observed":{"Deaths":55},"Population":257514,"Expected":{"Deaths":51},"Potentially":{"Excess":{"Deaths":5}}},
{"Year":2014,"Cause":{"of":{"Death":"Cancer"}},"State":{"FIPS":{"Code":"MT"}},"HHS":{"Region":8},"Age":{"Range":"0-54"},"Benchmark":"Floating","Locality":"Metropolitan","Observed":{"Deaths":52},"Population":257654,"Expected":{"Deaths":49},"Potentially":{"Excess":{"Deaths":7}}},
{"Year":2015,"Cause":{"of":{"Death":"Cancer"}},"State":{"FIPS":{"Code":"MT"}},"HHS":{"Region":8},"Age":{"Range":"0-54"},"Benchmark":"Floating","Locality":"Metropolitan","Observed":{"Deaths":71},"Population":257598,"Expected":{"Deaths":47},"Potentially":{"Excess":{"Deaths":27}}},
{"Year":2005,"Cause":{"of":{"Death":"Cancer"}},"State":{"FIPS":{"Code":"MT"}},"HHS":{"Region":8},"Age":{"Range":"0-54"},"Benchmark":"Floating","Locality":"Nonmetropolitan","Observed":{"Deaths":164},"Population":447326,"Expected":{"Deaths":112},"Potentially":{"Excess":{"Deaths":52}}},
{"Year":2006,"Cause":{"of":{"Death":"Cancer"}},"State":{"FIPS":{"Code":"MT"}},"HHS":{"Region":8},"Age":{"Range":"0-54"},"Benchmark":"Floating","Locality":"Nonmetropolitan","Observed":{"Deaths":120},"Population":449262,"Expected":{"Deaths":116},"Potentially":{"Excess":{"Deaths":10}}},
{"Year":2007,"Cause":{"of":{"Death":"Cancer"}},"State":{"FIPS":{"Code":"MT"}},"HHS":{"Region":8},"Age":{"Range":"0-54"},"Benchmark":"Floating","Locality":"Nonmetropolitan","Observed":{"Deaths":142},"Population":451022,"Expected":{"Deaths":117},"Potentially":{"Excess":{"Deaths":30}}},
{"Year":2008,"Cause":{"of":{"Death":"Cancer"}},"State":{"FIPS":{"Code":"MT"}},"HHS":{"Region":8},"Age":{"Range":"0-54"},"Benchmark":"Floating","Locality":"Nonmetropolitan","Observed":{"Deaths":95},"Population":451400,"Expected":{"Deaths":112},"Potentially":{"Excess":{"Deaths":0}}},
{"Year":2009,"Cause":{"of":{"Death":"Cancer"}},"State":{"FIPS":{"Code":"MT"}},"HHS":{"Region":8},"Age":{"Range":"0-54"},"Benchmark":"Floating","Locality":"Nonmetropolitan","Observed":{"Deaths":143},"Population":449253,"Expected":{"Deaths":108},"Potentially":{"Excess":{"Deaths":35}}},
{"Year":2010,"Cause":{"of":{"Death":"Cancer"}},"State":{"FIPS":{"Code":"MT"}},"HHS":{"Region":8},"Age":{"Range":"0-54"},"Benchmark":"Floating","Locality":"Nonmetropolitan","Observed":{"Deaths":133},"Population":447225,"Expected":{"Deaths":108},"Potentially":{"Excess":{"Deaths":29}}},
{"Year":2011,"Cause":{"of":{"Death":"Cancer"}},"State":{"FIPS":{"Code":"MT"}},"HHS":{"Region":8},"Age":{"Range":"0-54"},"Benchmark":"Floating","Locality":"Nonmetropolitan","Observed":{"Deaths":123},"Population":445135,"Expected":{"Deaths":102},"Potentially":{"Excess":{"Deaths":21}}},
{"Year":2012,"Cause":{"of":{"Death":"Cancer"}},"State":{"FIPS":{"Code":"MT"}},"HHS":{"Region":8},"Age":{"Range":"0-54"},"Benchmark":"Floating","Locality":"Nonmetropolitan","Observed":{"Deaths":122},"Population":443634,"Expected":{"Deaths":100},"Potentially":{"Excess":{"Deaths":24}}},
{"Year":2013,"Cause":{"of":{"Death":"Cancer"}},"State":{"FIPS":{"Code":"MT"}},"HHS":{"Region":8},"Age":{"Range":"0-54"},"Benchmark":"Floating","Locality":"Nonmetropolitan","Observed":{"Deaths":92},"Population":443727,"Expected":{"Deaths":94},"Potentially":{"Excess":{"Deaths":5}}},
{"Year":2014,"Cause":{"of":{"Death":"Cancer"}},"State":{"FIPS":{"Code":"MT"}},"HHS":{"Region":8},"Age":{"Range":"0-54"},"Benchmark":"Floating","Locality":"Nonmetropolitan","Observed":{"Deaths":102},"Population":444376,"Expected":{"Deaths":91},"Potentially":{"Excess":{"Deaths":13}}},
{"Year":2015,"Cause":{"of":{"Death":"Cancer"}},"State":{"FIPS":{"Code":"MT"}},"HHS":{"Region":8},"Age":{"Range":"0-54"},"Benchmark":"Floating","Locality":"Nonmetropolitan","Observed":{"Deaths":122},"Population":445861,"Expected":{"Deaths":85},"Potentially":{"Excess":{"Deaths":37}}},
{"Year":2005,"Cause":{"of":{"Death":"Stroke"}},"State":{"FIPS":{"Code":"MT"}},"HHS":{"Region":8},"Age":{"Range":"0-54"},"Benchmark":"Floating","Locality":"All","Observed":{"Deaths":21},"Population":699822,"Expected":{"Deaths":16},"Potentially":{"Excess":{"Deaths":5}}},
{"Year":2006,"Cause":{"of":{"Death":"Stroke"}},"State":{"FIPS":{"Code":"MT"}},"HHS":{"Region":8},"Age":{"Range":"0-54"},"Benchmark":"Floating","Locality":"All","Observed":{"Deaths":22},"Population":702856,"Expected":{"Deaths":17},"Potentially":{"Excess":{"Deaths":7}}},
{"Year":2007,"Cause":{"of":{"Death":"Stroke"}},"State":{"FIPS":{"Code":"MT"}},"HHS":{"Region":8},"Age":{"Range":"0-54"},"Benchmark":"Floating","Locality":"All","Observed":{"Deaths":24},"Population":705210,"Expected":{"Deaths":18},"Potentially":{"Excess":{"Deaths":6}}},
{"Year":2008,"Cause":{"of":{"Death":"Stroke"}},"State":{"FIPS":{"Code":"MT"}},"HHS":{"Region":8},"Age":{"Range":"0-54"},"Benchmark":"Floating","Locality":"All","Observed":{"Deaths":14},"Population":707295,"Expected":{"Deaths":16},"Potentially":{"Excess":{"Deaths":0}}},
{"Year":2009,"Cause":{"of":{"Death":"Stroke"}},"State":{"FIPS":{"Code":"MT"}},"HHS":{"Region":8},"Age":{"Range":"0-54"},"Benchmark":"Floating","Locality":"All","Observed":{"Deaths":22},"Population":705489,"Expected":{"Deaths":17},"Potentially":{"Excess":{"Deaths":5}}},
{"Year":2010,"Cause":{"of":{"Death":"Stroke"}},"State":{"FIPS":{"Code":"MT"}},"HHS":{"Region":8},"Age":{"Range":"0-54"},"Benchmark":"Floating","Locality":"All","Observed":{"Deaths":24},"Population":703815,"Expected":{"Deaths":16},"Potentially":{"Excess":{"Deaths":8}}},
{"Year":2011,"Cause":{"of":{"Death":"Stroke"}},"State":{"FIPS":{"Code":"MT"}},"HHS":{"Region":8},"Age":{"Range":"0-54"},"Benchmark":"Floating","Locality":"All","Observed":{"Deaths":18},"Population":701820,"Expected":{"Deaths":15},"Potentially":{"Excess":{"Deaths":3}}},
{"Year":2012,"Cause":{"of":{"Death":"Stroke"}},"State":{"FIPS":{"Code":"MT"}},"HHS":{"Region":8},"Age":{"Range":"0-54"},"Benchmark":"Floating","Locality":"All","Observed":{"Deaths":21},"Population":700019,"Expected":{"Deaths":15},"Potentially":{"Excess":{"Deaths":7}}},
{"Year":2013,"Cause":{"of":{"Death":"Stroke"}},"State":{"FIPS":{"Code":"MT"}},"HHS":{"Region":8},"Age":{"Range":"0-54"},"Benchmark":"Floating","Locality":"All","Observed":{"Deaths":20},"Population":701241,"Expected":{"Deaths":13},"Potentially":{"Excess":{"Deaths":7}}},
{"Year":2014,"Cause":{"of":{"Death":"Stroke"}},"State":{"FIPS":{"Code":"MT"}},"HHS":{"Region":8},"Age":{"Range":"0-54"},"Benchmark":"Floating","Locality":"All","Observed":{"Deaths":20},"Population":702030,"Expected":{"Deaths":13},"Potentially":{"Excess":{"Deaths":7}}},
{"Year":2015,"Cause":{"of":{"Death":"Stroke"}},"State":{"FIPS":{"Code":"MT"}},"HHS":{"Region":8},"Age":{"Range":"0-54"},"Benchmark":"Floating","Locality":"All","Observed":{"Deaths":14},"Population":703459,"Expected":{"Deaths":13},"Potentially":{"Excess":{"Deaths":4}}},
{"Year":2005,"Cause":{"of":{"Death":"Stroke"}},"State":{"FIPS":{"Code":"MT"}},"HHS":{"Region":8},"Age":{"Range":"0-54"},"Benchmark":"Floating","Locality":"Metropolitan","Observed":{"Deaths":"."},"Population":252496,"Expected":{"Deaths":"."},"Potentially":{"Excess":{"Deaths":"."}}},
{"Year":2006,"Cause":{"of":{"Death":"Stroke"}},"State":{"FIPS":{"Code":"MT"}},"HHS":{"Region":8},"Age":{"Range":"0-54"},"Benchmark":"Floating","Locality":"Metropolitan","Observed":{"Deaths":10},"Population":253594,"Expected":{"Deaths":6},"Potentially":{"Excess":{"Deaths":6}}},
{"Year":2007,"Cause":{"of":{"Death":"Stroke"}},"State":{"FIPS":{"Code":"MT"}},"HHS":{"Region":8},"Age":{"Range":"0-54"},"Benchmark":"Floating","Locality":"Metropolitan","Observed":{"Deaths":"."},"Population":254188,"Expected":{"Deaths":"."},"Potentially":{"Excess":{"Deaths":"."}}},
{"Year":2008,"Cause":{"of":{"Death":"Stroke"}},"State":{"FIPS":{"Code":"MT"}},"HHS":{"Region":8},"Age":{"Range":"0-54"},"Benchmark":"Floating","Locality":"Metropolitan","Observed":{"Deaths":"."},"Population":255895,"Expected":{"Deaths":"."},"Potentially":{"Excess":{"Deaths":"."}}},
{"Year":2009,"Cause":{"of":{"Death":"Stroke"}},"State":{"FIPS":{"Code":"MT"}},"HHS":{"Region":8},"Age":{"Range":"0-54"},"Benchmark":"Floating","Locality":"Metropolitan","Observed":{"Deaths":11},"Population":256236,"Expected":{"Deaths":6},"Potentially":{"Excess":{"Deaths":5}}},
{"Year":2010,"Cause":{"of":{"Death":"Stroke"}},"State":{"FIPS":{"Code":"MT"}},"HHS":{"Region":8},"Age":{"Range":"0-54"},"Benchmark":"Floating","Locality":"Metropolitan","Observed":{"Deaths":"."},"Population":256590,"Expected":{"Deaths":"."},"Potentially":{"Excess":{"Deaths":"."}}},
{"Year":2011,"Cause":{"of":{"Death":"Stroke"}},"State":{"FIPS":{"Code":"MT"}},"HHS":{"Region":8},"Age":{"Range":"0-54"},"Benchmark":"Floating","Locality":"Metropolitan","Observed":{"Deaths":"."},"Population":256685,"Expected":{"Deaths":"."},"Potentially":{"Excess":{"Deaths":"."}}},
{"Year":2012,"Cause":{"of":{"Death":"Stroke"}},"State":{"FIPS":{"Code":"MT"}},"HHS":{"Region":8},"Age":{"Range":"0-54"},"Benchmark":"Floating","Locality":"Metropolitan","Observed":{"Deaths":11},"Population":256385,"Expected":{"Deaths":5},"Potentially":{"Excess":{"Deaths":6}}},
{"Year":2013,"Cause":{"of":{"Death":"Stroke"}},"State":{"FIPS":{"Code":"MT"}},"HHS":{"Region":8},"Age":{"Range":"0-54"},"Benchmark":"Floating","Locality":"Metropolitan","Observed":{"Deaths":11},"Population":257514,"Expected":{"Deaths":5},"Potentially":{"Excess":{"Deaths":6}}},
{"Year":2014,"Cause":{"of":{"Death":"Stroke"}},"State":{"FIPS":{"Code":"MT"}},"HHS":{"Region":8},"Age":{"Range":"0-54"},"Benchmark":"Floating","Locality":"Metropolitan","Observed":{"Deaths":"."},"Population":257654,"Expected":{"Deaths":"."},"Potentially":{"Excess":{"Deaths":"."}}},
{"Year":2015,"Cause":{"of":{"Death":"Stroke"}},"State":{"FIPS":{"Code":"MT"}},"HHS":{"Region":8},"Age":{"Range":"0-54"},"Benchmark":"Floating","Locality":"Metropolitan","Observed":{"Deaths":"."},"Population":257598,"Expected":{"Deaths":"."},"Potentially":{"Excess":{"Deaths":"."}}},
{"Year":2005,"Cause":{"of":{"Death":"Stroke"}},"State":{"FIPS":{"Code":"MT"}},"HHS":{"Region":8},"Age":{"Range":"0-54"},"Benchmark":"Floating","Locality":"Nonmetropolitan","Observed":{"Deaths":18},"Population":447326,"Expected":{"Deaths":10},"Potentially":{"Excess":{"Deaths":8}}},
{"Year":2006,"Cause":{"of":{"Death":"Stroke"}},"State":{"FIPS":{"Code":"MT"}},"HHS":{"Region":8},"Age":{"Range":"0-54"},"Benchmark":"Floating","Locality":"Nonmetropolitan","Observed":{"Deaths":12},"Population":449262,"Expected":{"Deaths":11},"Potentially":{"Excess":{"Deaths":1}}},
{"Year":2007,"Cause":{"of":{"Death":"Stroke"}},"State":{"FIPS":{"Code":"MT"}},"HHS":{"Region":8},"Age":{"Range":"0-54"},"Benchmark":"Floating","Locality":"Nonmetropolitan","Observed":{"Deaths":16},"Population":451022,"Expected":{"Deaths":12},"Potentially":{"Excess":{"Deaths":4}}},
{"Year":2008,"Cause":{"of":{"Death":"Stroke"}},"State":{"FIPS":{"Code":"MT"}},"HHS":{"Region":8},"Age":{"Range":"0-54"},"Benchmark":"Floating","Locality":"Nonmetropolitan","Observed":{"Deaths":13},"Population":451400,"Expected":{"Deaths":10},"Potentially":{"Excess":{"Deaths":3}}},
{"Year":2009,"Cause":{"of":{"Death":"Stroke"}},"State":{"FIPS":{"Code":"MT"}},"HHS":{"Region":8},"Age":{"Range":"0-54"},"Benchmark":"Floating","Locality":"Nonmetropolitan","Observed":{"Deaths":11},"Population":449253,"Expected":{"Deaths":11},"Potentially":{"Excess":{"Deaths":1}}},
{"Year":2010,"Cause":{"of":{"Death":"Stroke"}},"State":{"FIPS":{"Code":"MT"}},"HHS":{"Region":8},"Age":{"Range":"0-54"},"Benchmark":"Floating","Locality":"Nonmetropolitan","Observed":{"Deaths":16},"Population":447225,"Expected":{"Deaths":10},"Potentially":{"Excess":{"Deaths":6}}},
{"Year":2011,"Cause":{"of":{"Death":"Stroke"}},"State":{"FIPS":{"Code":"MT"}},"HHS":{"Region":8},"Age":{"Range":"0-54"},"Benchmark":"Floating","Locality":"Nonmetropolitan","Observed":{"Deaths":12},"Population":445135,"Expected":{"Deaths":10},"Potentially":{"Excess":{"Deaths":2}}},
{"Year":2012,"Cause":{"of":{"Death":"Stroke"}},"State":{"FIPS":{"Code":"MT"}},"HHS":{"Region":8},"Age":{"Range":"0-54"},"Benchmark":"Floating","Locality":"Nonmetropolitan","Observed":{"Deaths":10},"Population":443634,"Expected":{"Deaths":9},"Potentially":{"Excess":{"Deaths":1}}},
{"Year":2013,"Cause":{"of":{"Death":"Stroke"}},"State":{"FIPS":{"Code":"MT"}},"HHS":{"Region":8},"Age":{"Range":"0-54"},"Benchmark":"Floating","Locality":"Nonmetropolitan","Observed":{"Deaths":"."},"Population":443727,"Expected":{"Deaths":"."},"Potentially":{"Excess":{"Deaths":"."}}},
{"Year":2014,"Cause":{"of":{"Death":"Stroke"}},"State":{"FIPS":{"Code":"MT"}},"HHS":{"Region":8},"Age":{"Range":"0-54"},"Benchmark":"Floating","Locality":"Nonmetropolitan","Observed":{"Deaths":13},"Population":444376,"Expected":{"Deaths":9},"Potentially":{"Excess":{"Deaths":4}}},
{"Year":2015,"Cause":{"of":{"Death":"Stroke"}},"State":{"FIPS":{"Code":"MT"}},"HHS":{"Region":8},"Age":{"Range":"0-54"},"Benchmark":"Floating","Locality":"Nonmetropolitan","Observed":{"Deaths":"."},"Population":445861,"Expected":{"Deaths":"."},"Potentially":{"Excess":{"Deaths":"."}}},
{"Year":2005,"Cause":{"of":{"Death":"Chronic Lower Respiratory Disease"}},"State":{"FIPS":{"Code":"MT"}},"HHS":{"Region":8},"Age":{"Range":"0-54"},"Benchmark":"Floating","Locality":"All","Observed":{"Deaths":19},"Population":699822,"Expected":{"Deaths":10},"Potentially":{"Excess":{"Deaths":9}}},
{"Year":2006,"Cause":{"of":{"Death":"Chronic Lower Respiratory Disease"}},"State":{"FIPS":{"Code":"MT"}},"HHS":{"Region":8},"Age":{"Range":"0-54"},"Benchmark":"Floating","Locality":"All","Observed":{"Deaths":16},"Population":702856,"Expected":{"Deaths":11},"Potentially":{"Excess":{"Deaths":7}}},
{"Year":2007,"Cause":{"of":{"Death":"Chronic Lower Respiratory Disease"}},"State":{"FIPS":{"Code":"MT"}},"HHS":{"Region":8},"Age":{"Range":"0-54"},"Benchmark":"Floating","Locality":"All","Observed":{"Deaths":19},"Population":705210,"Expected":{"Deaths":10},"Potentially":{"Excess":{"Deaths":9}}},
{"Year":2008,"Cause":{"of":{"Death":"Chronic Lower Respiratory Disease"}},"State":{"FIPS":{"Code":"MT"}},"HHS":{"Region":8},"Age":{"Range":"0-54"},"Benchmark":"Floating","Locality":"All","Observed":{"Deaths":23},"Population":707295,"Expected":{"Deaths":9},"Potentially":{"Excess":{"Deaths":14}}},
{"Year":2009,"Cause":{"of":{"Death":"Chronic Lower Respiratory Disease"}},"State":{"FIPS":{"Code":"MT"}},"HHS":{"Region":8},"Age":{"Range":"0-54"},"Benchmark":"Floating","Locality":"All","Observed":{"Deaths":16},"Population":705489,"Expected":{"Deaths":10},"Potentially":{"Excess":{"Deaths":7}}},
{"Year":2010,"Cause":{"of":{"Death":"Chronic Lower Respiratory Disease"}},"State":{"FIPS":{"Code":"MT"}},"HHS":{"Region":8},"Age":{"Range":"0-54"},"Benchmark":"Floating","Locality":"All","Observed":{"Deaths":19},"Population":703815,"Expected":{"Deaths":10},"Potentially":{"Excess":{"Deaths":10}}},
{"Year":2011,"Cause":{"of":{"Death":"Chronic Lower Respiratory Disease"}},"State":{"FIPS":{"Code":"MT"}},"HHS":{"Region":8},"Age":{"Range":"0-54"},"Benchmark":"Floating","Locality":"All","Observed":{"Deaths":17},"Population":701820,"Expected":{"Deaths":11},"Potentially":{"Excess":{"Deaths":7}}},
{"Year":2012,"Cause":{"of":{"Death":"Chronic Lower Respiratory Disease"}},"State":{"FIPS":{"Code":"MT"}},"HHS":{"Region":8},"Age":{"Range":"0-54"},"Benchmark":"Floating","Locality":"All","Observed":{"Deaths":21},"Population":700019,"Expected":{"Deaths":10},"Potentially":{"Excess":{"Deaths":11}}},
{"Year":2013,"Cause":{"of":{"Death":"Chronic Lower Respiratory Disease"}},"State":{"FIPS":{"Code":"MT"}},"HHS":{"Region":8},"Age":{"Range":"0-54"},"Benchmark":"Floating","Locality":"All","Observed":{"Deaths":15},"Population":701241,"Expected":{"Deaths":11},"Potentially":{"Excess":{"Deaths":4}}},
{"Year":2014,"Cause":{"of":{"Death":"Chronic Lower Respiratory Disease"}},"State":{"FIPS":{"Code":"MT"}},"HHS":{"Region":8},"Age":{"Range":"0-54"},"Benchmark":"Floating","Locality":"All","Observed":{"Deaths":17},"Population":702030,"Expected":{"Deaths":10},"Potentially":{"Excess":{"Deaths":7}}},
{"Year":2015,"Cause":{"of":{"Death":"Chronic Lower Respiratory Disease"}},"State":{"FIPS":{"Code":"MT"}},"HHS":{"Region":8},"Age":{"Range":"0-54"},"Benchmark":"Floating","Locality":"All","Observed":{"Deaths":17},"Population":703459,"Expected":{"Deaths":10},"Potentially":{"Excess":{"Deaths":7}}},
{"Year":2005,"Cause":{"of":{"Death":"Chronic Lower Respiratory Disease"}},"State":{"FIPS":{"Code":"MT"}},"HHS":{"Region":8},"Age":{"Range":"0-54"},"Benchmark":"Floating","Locality":"Metropolitan","Observed":{"Deaths":"."},"Population":252496,"Expected":{"Deaths":"."},"Potentially":{"Excess":{"Deaths":"."}}},
{"Year":2006,"Cause":{"of":{"Death":"Chronic Lower Respiratory Disease"}},"State":{"FIPS":{"Code":"MT"}},"HHS":{"Region":8},"Age":{"Range":"0-54"},"Benchmark":"Floating","Locality":"Metropolitan","Observed":{"Deaths":"."},"Population":253594,"Expected":{"Deaths":"."},"Potentially":{"Excess":{"Deaths":"."}}},
{"Year":2007,"Cause":{"of":{"Death":"Chronic Lower Respiratory Disease"}},"State":{"FIPS":{"Code":"MT"}},"HHS":{"Region":8},"Age":{"Range":"0-54"},"Benchmark":"Floating","Locality":"Metropolitan","Observed":{"Deaths":"."},"Population":254188,"Expected":{"Deaths":"."},"Potentially":{"Excess":{"Deaths":"."}}},
{"Year":2008,"Cause":{"of":{"Death":"Chronic Lower Respiratory Disease"}},"State":{"FIPS":{"Code":"MT"}},"HHS":{"Region":8},"Age":{"Range":"0-54"},"Benchmark":"Floating","Locality":"Metropolitan","Observed":{"Deaths":10},"Population":255895,"Expected":{"Deaths":3},"Potentially":{"Excess":{"Deaths":7}}},
{"Year":2009,"Cause":{"of":{"Death":"Chronic Lower Respiratory Disease"}},"State":{"FIPS":{"Code":"MT"}},"HHS":{"Region":8},"Age":{"Range":"0-54"},"Benchmark":"Floating","Locality":"Metropolitan","Observed":{"Deaths":"."},"Population":256236,"Expected":{"Deaths":"."},"Potentially":{"Excess":{"Deaths":"."}}},
{"Year":2010,"Cause":{"of":{"Death":"Chronic Lower Respiratory Disease"}},"State":{"FIPS":{"Code":"MT"}},"HHS":{"Region":8},"Age":{"Range":"0-54"},"Benchmark":"Floating","Locality":"Metropolitan","Observed":{"Deaths":10},"Population":256590,"Expected":{"Deaths":4},"Potentially":{"Excess":{"Deaths":6}}},
{"Year":2011,"Cause":{"of":{"Death":"Chronic Lower Respiratory Disease"}},"State":{"FIPS":{"Code":"MT"}},"HHS":{"Region":8},"Age":{"Range":"0-54"},"Benchmark":"Floating","Locality":"Metropolitan","Observed":{"Deaths":"."},"Population":256685,"Expected":{"Deaths":"."},"Potentially":{"Excess":{"Deaths":"."}}},
{"Year":2012,"Cause":{"of":{"Death":"Chronic Lower Respiratory Disease"}},"State":{"FIPS":{"Code":"MT"}},"HHS":{"Region":8},"Age":{"Range":"0-54"},"Benchmark":"Floating","Locality":"Metropolitan","Observed":{"Deaths":10},"Population":256385,"Expected":{"Deaths":4},"Potentially":{"Excess":{"Deaths":6}}},
{"Year":2013,"Cause":{"of":{"Death":"Chronic Lower Respiratory Disease"}},"State":{"FIPS":{"Code":"MT"}},"HHS":{"Region":8},"Age":{"Range":"0-54"},"Benchmark":"Floating","Locality":"Metropolitan","Observed":{"Deaths":"."},"Population":257514,"Expected":{"Deaths":"."},"Potentially":{"Excess":{"Deaths":"."}}},
{"Year":2014,"Cause":{"of":{"Death":"Chronic Lower Respiratory Disease"}},"State":{"FIPS":{"Code":"MT"}},"HHS":{"Region":8},"Age":{"Range":"0-54"},"Benchmark":"Floating","Locality":"Metropolitan","Observed":{"Deaths":"."},"Population":257654,"Expected":{"Deaths":"."},"Potentially":{"Excess":{"Deaths":"."}}},
{"Year":2015,"Cause":{"of":{"Death":"Chronic Lower Respiratory Disease"}},"State":{"FIPS":{"Code":"MT"}},"HHS":{"Region":8},"Age":{"Range":"0-54"},"Benchmark":"Floating","Locality":"Metropolitan","Observed":{"Deaths":10},"Population":257598,"Expected":{"Deaths":3},"Potentially":{"Excess":{"Deaths":7}}},
{"Year":2005,"Cause":{"of":{"Death":"Chronic Lower Respiratory Disease"}},"State":{"FIPS":{"Code":"MT"}},"HHS":{"Region":8},"Age":{"Range":"0-54"},"Benchmark":"Floating","Locality":"Nonmetropolitan","Observed":{"Deaths":10},"Population":447326,"Expected":{"Deaths":7},"Potentially":{"Excess":{"Deaths":3}}},
{"Year":2006,"Cause":{"of":{"Death":"Chronic Lower Respiratory Disease"}},"State":{"FIPS":{"Code":"MT"}},"HHS":{"Region":8},"Age":{"Range":"0-54"},"Benchmark":"Floating","Locality":"Nonmetropolitan","Observed":{"Deaths":13},"Population":449262,"Expected":{"Deaths":7},"Potentially":{"Excess":{"Deaths":8}}},
{"Year":2007,"Cause":{"of":{"Death":"Chronic Lower Respiratory Disease"}},"State":{"FIPS":{"Code":"MT"}},"HHS":{"Region":8},"Age":{"Range":"0-54"},"Benchmark":"Floating","Locality":"Nonmetropolitan","Observed":{"Deaths":14},"Population":451022,"Expected":{"Deaths":7},"Potentially":{"Excess":{"Deaths":8}}},
{"Year":2008,"Cause":{"of":{"Death":"Chronic Lower Respiratory Disease"}},"State":{"FIPS":{"Code":"MT"}},"HHS":{"Region":8},"Age":{"Range":"0-54"},"Benchmark":"Floating","Locality":"Nonmetropolitan","Observed":{"Deaths":13},"Population":451400,"Expected":{"Deaths":6},"Potentially":{"Excess":{"Deaths":7}}},
{"Year":2009,"Cause":{"of":{"Death":"Chronic Lower Respiratory Disease"}},"State":{"FIPS":{"Code":"MT"}},"HHS":{"Region":8},"Age":{"Range":"0-54"},"Benchmark":"Floating","Locality":"Nonmetropolitan","Observed":{"Deaths":14},"Population":449253,"Expected":{"Deaths":6},"Potentially":{"Excess":{"Deaths":8}}},
{"Year":2010,"Cause":{"of":{"Death":"Chronic Lower Respiratory Disease"}},"State":{"FIPS":{"Code":"MT"}},"HHS":{"Region":8},"Age":{"Range":"0-54"},"Benchmark":"Floating","Locality":"Nonmetropolitan","Observed":{"Deaths":"."},"Population":447225,"Expected":{"Deaths":"."},"Potentially":{"Excess":{"Deaths":"."}}},
{"Year":2011,"Cause":{"of":{"Death":"Chronic Lower Respiratory Disease"}},"State":{"FIPS":{"Code":"MT"}},"HHS":{"Region":8},"Age":{"Range":"0-54"},"Benchmark":"Floating","Locality":"Nonmetropolitan","Observed":{"Deaths":12},"Population":445135,"Expected":{"Deaths":7},"Potentially":{"Excess":{"Deaths":5}}},
{"Year":2012,"Cause":{"of":{"Death":"Chronic Lower Respiratory Disease"}},"State":{"FIPS":{"Code":"MT"}},"HHS":{"Region":8},"Age":{"Range":"0-54"},"Benchmark":"Floating","Locality":"Nonmetropolitan","Observed":{"Deaths":11},"Population":443634,"Expected":{"Deaths":7},"Potentially":{"Excess":{"Deaths":5}}},
{"Year":2013,"Cause":{"of":{"Death":"Chronic Lower Respiratory Disease"}},"State":{"FIPS":{"Code":"MT"}},"HHS":{"Region":8},"Age":{"Range":"0-54"},"Benchmark":"Floating","Locality":"Nonmetropolitan","Observed":{"Deaths":12},"Population":443727,"Expected":{"Deaths":7},"Potentially":{"Excess":{"Deaths":5}}},
{"Year":2014,"Cause":{"of":{"Death":"Chronic Lower Respiratory Disease"}},"State":{"FIPS":{"Code":"MT"}},"HHS":{"Region":8},"Age":{"Range":"0-54"},"Benchmark":"Floating","Locality":"Nonmetropolitan","Observed":{"Deaths":10},"Population":444376,"Expected":{"Deaths":7},"Potentially":{"Excess":{"Deaths":5}}},
{"Year":2015,"Cause":{"of":{"Death":"Chronic Lower Respiratory Disease"}},"State":{"FIPS":{"Code":"MT"}},"HHS":{"Region":8},"Age":{"Range":"0-54"},"Benchmark":"Floating","Locality":"Nonmetropolitan","Observed":{"Deaths":"."},"Population":445861,"Expected":{"Deaths":"."},"Potentially":{"Excess":{"Deaths":"."}}},
{"Year":2005,"Cause":{"of":{"Death":"Unintentional Injury"}},"State":{"FIPS":{"Code":"MT"}},"HHS":{"Region":8},"Age":{"Range":"0-54"},"Benchmark":"Floating","Locality":"All","Observed":{"Deaths":279},"Population":699822,"Expected":{"Deaths":112},"Potentially":{"Excess":{"Deaths":167}}},
{"Year":2006,"Cause":{"of":{"Death":"Unintentional Injury"}},"State":{"FIPS":{"Code":"MT"}},"HHS":{"Region":8},"Age":{"Range":"0-54"},"Benchmark":"Floating","Locality":"All","Observed":{"Deaths":321},"Population":702856,"Expected":{"Deaths":123},"Potentially":{"Excess":{"Deaths":198}}},
{"Year":2007,"Cause":{"of":{"Death":"Unintentional Injury"}},"State":{"FIPS":{"Code":"MT"}},"HHS":{"Region":8},"Age":{"Range":"0-54"},"Benchmark":"Floating","Locality":"All","Observed":{"Deaths":344},"Population":705210,"Expected":{"Deaths":128},"Potentially":{"Excess":{"Deaths":216}}},
{"Year":2008,"Cause":{"of":{"Death":"Unintentional Injury"}},"State":{"FIPS":{"Code":"MT"}},"HHS":{"Region":8},"Age":{"Range":"0-54"},"Benchmark":"Floating","Locality":"All","Observed":{"Deaths":348},"Population":707295,"Expected":{"Deaths":129},"Potentially":{"Excess":{"Deaths":219}}},
{"Year":2009,"Cause":{"of":{"Death":"Unintentional Injury"}},"State":{"FIPS":{"Code":"MT"}},"HHS":{"Region":8},"Age":{"Range":"0-54"},"Benchmark":"Floating","Locality":"All","Observed":{"Deaths":345},"Population":705489,"Expected":{"Deaths":122},"Potentially":{"Excess":{"Deaths":223}}},
{"Year":2010,"Cause":{"of":{"Death":"Unintentional Injury"}},"State":{"FIPS":{"Code":"MT"}},"HHS":{"Region":8},"Age":{"Range":"0-54"},"Benchmark":"Floating","Locality":"All","Observed":{"Deaths":292},"Population":703815,"Expected":{"Deaths":118},"Potentially":{"Excess":{"Deaths":174}}},
{"Year":2011,"Cause":{"of":{"Death":"Unintentional Injury"}},"State":{"FIPS":{"Code":"MT"}},"HHS":{"Region":8},"Age":{"Range":"0-54"},"Benchmark":"Floating","Locality":"All","Observed":{"Deaths":293},"Population":701820,"Expected":{"Deaths":119},"Potentially":{"Excess":{"Deaths":174}}},
{"Year":2012,"Cause":{"of":{"Death":"Unintentional Injury"}},"State":{"FIPS":{"Code":"MT"}},"HHS":{"Region":8},"Age":{"Range":"0-54"},"Benchmark":"Floating","Locality":"All","Observed":{"Deaths":284},"Population":700019,"Expected":{"Deaths":123},"Potentially":{"Excess":{"Deaths":161}}},
{"Year":2013,"Cause":{"of":{"Death":"Unintentional Injury"}},"State":{"FIPS":{"Code":"MT"}},"HHS":{"Region":8},"Age":{"Range":"0-54"},"Benchmark":"Floating","Locality":"All","Observed":{"Deaths":317},"Population":701241,"Expected":{"Deaths":128},"Potentially":{"Excess":{"Deaths":189}}},
{"Year":2014,"Cause":{"of":{"Death":"Unintentional Injury"}},"State":{"FIPS":{"Code":"MT"}},"HHS":{"Region":8},"Age":{"Range":"0-54"},"Benchmark":"Floating","Locality":"All","Observed":{"Deaths":263},"Population":702030,"Expected":{"Deaths":127},"Potentially":{"Excess":{"Deaths":136}}},
{"Year":2015,"Cause":{"of":{"Death":"Unintentional Injury"}},"State":{"FIPS":{"Code":"MT"}},"HHS":{"Region":8},"Age":{"Range":"0-54"},"Benchmark":"Floating","Locality":"All","Observed":{"Deaths":295},"Population":703459,"Expected":{"Deaths":132},"Potentially":{"Excess":{"Deaths":163}}},
{"Year":2005,"Cause":{"of":{"Death":"Unintentional Injury"}},"State":{"FIPS":{"Code":"MT"}},"HHS":{"Region":8},"Age":{"Range":"0-54"},"Benchmark":"Floating","Locality":"Metropolitan","Observed":{"Deaths":88},"Population":252496,"Expected":{"Deaths":41},"Potentially":{"Excess":{"Deaths":49}}},
{"Year":2006,"Cause":{"of":{"Death":"Unintentional Injury"}},"State":{"FIPS":{"Code":"MT"}},"HHS":{"Region":8},"Age":{"Range":"0-54"},"Benchmark":"Floating","Locality":"Metropolitan","Observed":{"Deaths":74},"Population":253594,"Expected":{"Deaths":44},"Potentially":{"Excess":{"Deaths":30}}},
{"Year":2007,"Cause":{"of":{"Death":"Unintentional Injury"}},"State":{"FIPS":{"Code":"MT"}},"HHS":{"Region":8},"Age":{"Range":"0-54"},"Benchmark":"Floating","Locality":"Metropolitan","Observed":{"Deaths":85},"Population":254188,"Expected":{"Deaths":46},"Potentially":{"Excess":{"Deaths":39}}},
{"Year":2008,"Cause":{"of":{"Death":"Unintentional Injury"}},"State":{"FIPS":{"Code":"MT"}},"HHS":{"Region":8},"Age":{"Range":"0-54"},"Benchmark":"Floating","Locality":"Metropolitan","Observed":{"Deaths":97},"Population":255895,"Expected":{"Deaths":47},"Potentially":{"Excess":{"Deaths":50}}},
{"Year":2009,"Cause":{"of":{"Death":"Unintentional Injury"}},"State":{"FIPS":{"Code":"MT"}},"HHS":{"Region":8},"Age":{"Range":"0-54"},"Benchmark":"Floating","Locality":"Metropolitan","Observed":{"Deaths":92},"Population":256236,"Expected":{"Deaths":45},"Potentially":{"Excess":{"Deaths":47}}},
{"Year":2010,"Cause":{"of":{"Death":"Unintentional Injury"}},"State":{"FIPS":{"Code":"MT"}},"HHS":{"Region":8},"Age":{"Range":"0-54"},"Benchmark":"Floating","Locality":"Metropolitan","Observed":{"Deaths":97},"Population":256590,"Expected":{"Deaths":43},"Potentially":{"Excess":{"Deaths":54}}},
{"Year":2011,"Cause":{"of":{"Death":"Unintentional Injury"}},"State":{"FIPS":{"Code":"MT"}},"HHS":{"Region":8},"Age":{"Range":"0-54"},"Benchmark":"Floating","Locality":"Metropolitan","Observed":{"Deaths":74},"Population":256685,"Expected":{"Deaths":44},"Potentially":{"Excess":{"Deaths":30}}},
{"Year":2012,"Cause":{"of":{"Death":"Unintentional Injury"}},"State":{"FIPS":{"Code":"MT"}},"HHS":{"Region":8},"Age":{"Range":"0-54"},"Benchmark":"Floating","Locality":"Metropolitan","Observed":{"Deaths":74},"Population":256385,"Expected":{"Deaths":45},"Potentially":{"Excess":{"Deaths":30}}},
{"Year":2013,"Cause":{"of":{"Death":"Unintentional Injury"}},"State":{"FIPS":{"Code":"MT"}},"HHS":{"Region":8},"Age":{"Range":"0-54"},"Benchmark":"Floating","Locality":"Metropolitan","Observed":{"Deaths":100},"Population":257514,"Expected":{"Deaths":47},"Potentially":{"Excess":{"Deaths":53}}},
{"Year":2014,"Cause":{"of":{"Death":"Unintentional Injury"}},"State":{"FIPS":{"Code":"MT"}},"HHS":{"Region":8},"Age":{"Range":"0-54"},"Benchmark":"Floating","Locality":"Metropolitan","Observed":{"Deaths":67},"Population":257654,"Expected":{"Deaths":47},"Potentially":{"Excess":{"Deaths":20}}},
{"Year":2015,"Cause":{"of":{"Death":"Unintentional Injury"}},"State":{"FIPS":{"Code":"MT"}},"HHS":{"Region":8},"Age":{"Range":"0-54"},"Benchmark":"Floating","Locality":"Metropolitan","Observed":{"Deaths":76},"Population":257598,"Expected":{"Deaths":49},"Potentially":{"Excess":{"Deaths":27}}},
{"Year":2005,"Cause":{"of":{"Death":"Unintentional Injury"}},"State":{"FIPS":{"Code":"MT"}},"HHS":{"Region":8},"Age":{"Range":"0-54"},"Benchmark":"Floating","Locality":"Nonmetropolitan","Observed":{"Deaths":191},"Population":447326,"Expected":{"Deaths":72},"Potentially":{"Excess":{"Deaths":119}}},
{"Year":2006,"Cause":{"of":{"Death":"Unintentional Injury"}},"State":{"FIPS":{"Code":"MT"}},"HHS":{"Region":8},"Age":{"Range":"0-54"},"Benchmark":"Floating","Locality":"Nonmetropolitan","Observed":{"Deaths":247},"Population":449262,"Expected":{"Deaths":78},"Potentially":{"Excess":{"Deaths":169}}},
{"Year":2007,"Cause":{"of":{"Death":"Unintentional Injury"}},"State":{"FIPS":{"Code":"MT"}},"HHS":{"Region":8},"Age":{"Range":"0-54"},"Benchmark":"Floating","Locality":"Nonmetropolitan","Observed":{"Deaths":259},"Population":451022,"Expected":{"Deaths":82},"Potentially":{"Excess":{"Deaths":177}}},
{"Year":2008,"Cause":{"of":{"Death":"Unintentional Injury"}},"State":{"FIPS":{"Code":"MT"}},"HHS":{"Region":8},"Age":{"Range":"0-54"},"Benchmark":"Floating","Locality":"Nonmetropolitan","Observed":{"Deaths":251},"Population":451400,"Expected":{"Deaths":82},"Potentially":{"Excess":{"Deaths":169}}},
{"Year":2009,"Cause":{"of":{"Death":"Unintentional Injury"}},"State":{"FIPS":{"Code":"MT"}},"HHS":{"Region":8},"Age":{"Range":"0-54"},"Benchmark":"Floating","Locality":"Nonmetropolitan","Observed":{"Deaths":253},"Population":449253,"Expected":{"Deaths":78},"Potentially":{"Excess":{"Deaths":175}}},
{"Year":2010,"Cause":{"of":{"Death":"Unintentional Injury"}},"State":{"FIPS":{"Code":"MT"}},"HHS":{"Region":8},"Age":{"Range":"0-54"},"Benchmark":"Floating","Locality":"Nonmetropolitan","Observed":{"Deaths":195},"Population":447225,"Expected":{"Deaths":75},"Potentially":{"Excess":{"Deaths":120}}},
{"Year":2011,"Cause":{"of":{"Death":"Unintentional Injury"}},"State":{"FIPS":{"Code":"MT"}},"HHS":{"Region":8},"Age":{"Range":"0-54"},"Benchmark":"Floating","Locality":"Nonmetropolitan","Observed":{"Deaths":219},"Population":445135,"Expected":{"Deaths":75},"Potentially":{"Excess":{"Deaths":144}}},
{"Year":2012,"Cause":{"of":{"Death":"Unintentional Injury"}},"State":{"FIPS":{"Code":"MT"}},"HHS":{"Region":8},"Age":{"Range":"0-54"},"Benchmark":"Floating","Locality":"Nonmetropolitan","Observed":{"Deaths":210},"Population":443634,"Expected":{"Deaths":78},"Potentially":{"Excess":{"Deaths":132}}},
{"Year":2013,"Cause":{"of":{"Death":"Unintentional Injury"}},"State":{"FIPS":{"Code":"MT"}},"HHS":{"Region":8},"Age":{"Range":"0-54"},"Benchmark":"Floating","Locality":"Nonmetropolitan","Observed":{"Deaths":217},"Population":443727,"Expected":{"Deaths":81},"Potentially":{"Excess":{"Deaths":136}}},
{"Year":2014,"Cause":{"of":{"Death":"Unintentional Injury"}},"State":{"FIPS":{"Code":"MT"}},"HHS":{"Region":8},"Age":{"Range":"0-54"},"Benchmark":"Floating","Locality":"Nonmetropolitan","Observed":{"Deaths":196},"Population":444376,"Expected":{"Deaths":80},"Potentially":{"Excess":{"Deaths":116}}},
{"Year":2015,"Cause":{"of":{"Death":"Unintentional Injury"}},"State":{"FIPS":{"Code":"MT"}},"HHS":{"Region":8},"Age":{"Range":"0-54"},"Benchmark":"Floating","Locality":"Nonmetropolitan","Observed":{"Deaths":219},"Population":445861,"Expected":{"Deaths":84},"Potentially":{"Excess":{"Deaths":135}}}
]